{"nodes": [{"id": "docs_home_yt_modified_home_page", "label": "YT Modified Home Page", "file_type": "code", "source_file": "docs/home.html", "source_location": null, "source_url": null, "captured_at": null, "author": null, "contributor": null}], "edges": [{"source": "docs_home_yt_modified_home_page", "target": "ui_home_yt_modified_home_page", "relation": "semantically_similar_to", "confidence": "INFERRED", "confidence_score": 0.95, "source_file": "docs/home.html", "source_location": null, "weight": 1.0}], "hyperedges": []}