{"nodes": [{"id": "users_bara_shaban_personal_yt_dlp_backend_mobile_readme_md", "label": "README.md", "file_type": "document", "source_file": "mobile/README.md", "source_location": "L1"}, {"id": "mobile_readme_ai_wa7shtube_mobile", "label": "AI-Wa7shTube Mobile", "file_type": "document", "source_file": "mobile/README.md", "source_location": "L1"}, {"id": "mobile_readme_run", "label": "Run", "file_type": "document", "source_file": "mobile/README.md", "source_location": "L5"}, {"id": "mobile_readme_share_on_real_phones", "label": "Share on real phones", "file_type": "document", "source_file": "mobile/README.md", "source_location": "L45"}], "edges": [{"source": "users_bara_shaban_personal_yt_dlp_backend_mobile_readme_md", "target": "mobile_readme_ai_wa7shtube_mobile", "relation": "contains", "confidence": "EXTRACTED", "source_file": "mobile/README.md", "source_location": "L1", "weight": 1.0}, {"source": "mobile_readme_ai_wa7shtube_mobile", "target": "mobile_readme_run", "relation": "contains", "confidence": "EXTRACTED", "source_file": "mobile/README.md", "source_location": "L5", "weight": 1.0}, {"source": "mobile_readme_ai_wa7shtube_mobile", "target": "mobile_readme_share_on_real_phones", "relation": "contains", "confidence": "EXTRACTED", "source_file": "mobile/README.md", "source_location": "L45", "weight": 1.0}], "input_tokens": 0, "output_tokens": 0}